{
  "name": "List of known URL Shorteners domains",
  "version": 3,
  "description": "Event contains one or more entries of known Shorteners domains",
  "matching_attributes": [
    "domain",
    "hostname",
    "domain|ip",
    "url",
    "uri"
  ],
  "list": [
    "1url.com",
    "adcraft.co",
    "adcrun.ch",
    "adflav.com",
    "adf.ly",
    "aka.gr",
    "amzn.to",
    "bc.vc",
    "bee4.biz",
    "bit.do",
    "bit.ly",
    "bitly.com",
    "buff.ly",
    "buzurl.com",
    "cektkp.com",
    "cur.lv",
    "cut.by",
    "cutt.us",
    "db.tt",
    "dft.ba",
    "filoops.info",
    "fun.ly",
    "fzy.co",
    "gog.li",
    "golinks.co",
    "goo.gl",
    "hit.my",
    "hyperurl.co",
    "id.tl",
    "is.gd",
    "ity.im",
    "j.mp",
    "linkto.im",
    "link.zip.net",
    "lnk.co",
    "lnkd.in",
    "mcaf.ee",
    "nov.io",
    "ow.ly",
    "p6l.org",
    "picz.us",
    "po.st",
    "prettylinkpro.com",
    "q.gs",
    "qr.ae",
    "qr.net",
    "scrnch.me",
    "shortquik.com",
    "sk.gy",
    "smarturl.it",
    "snip.ly",
    "su.pr",
    "t.co",
    "tiny.cc",
    "tinyarrows.com",
    "tinyurl.com",
    "tota2.com",
    "tr.im",
    "tweez.me",
    "twitthis.com",
    "u.bb",
    "u.to",
    "v.gd",
    "vzturl.com",
    "wp.me",
    "x.co",
    "xlinkz.info",
    "xtu.me",
    "yourls.org",
    "youtu.be",
    "yu2.it",
    "zpag.es,
"4sq.com",
"7.ly",
"adfoc.us",
"admy.link",
"al.ly",
"any.gs",
"ay.gy",
"biturl.io",
"clockurl.com",
"doiop.com",
"dyo.gs",
"easyurl.net",
"fas.li",
"fave.co",
"filesonthe.net",
"flic.kr",
"frama.link",
"gentleurl.net",
"git.io",
"goo.cl",
"hda.me",
"hec.su",
"hotshorturl.com",
"keeplinks.me",
"kleinurl.de",
"lc.cx",
"lemde.fr",
"libr.ae",
"linkpaid.net",
"lnked.in",
"lnx.lu",
"lok.biz",
"lynk.my",
"megaline.co",
"miniurls.co",
"minu.me",
"normalurl.com",
"notlong.com",
"nubr.co",
"one-link.de",
"ouo.io",
"ouo.press",
"oxu.be",
"ph.dog",
"prettylinkpro.com",
"qqc.co",
"redd.it",
"s.id",
"safelinking.net",
"sdu.sk",
"shadyurl.com",
"shink.in",
"shorl.com",
"short.st",
"shorte.st",
"shorturl.com",
"shrinkee.com",
"shrinkurl.in",
"sptfy.com",
"t.cn",
"tcrn.ch",
"thinfi.com",
"tighturl.com",
"tldrify.com",
"tmblr.co",
"tubeviral.com",
"ultrafiles.net",
"urlbeat.net",
"urlpetite.fr",
"urlz.fr",
"viralurl.biz",
"viralurl.com",
"virl.ws",
"vur.me",
"vurl.bz",
"vurl.com",
"xlinkz.info",
"xn--hgi.ws",
"yyv.co",
"zi.ma",
"zzb.bz"
  ]
}
